abdur_phone_number_validator/__init__.py
abdur_phone_number_validator/validator.py
abdur_phone_number_validator-0.1.0.dist-info/METADATA
abdur_phone_number_validator-0.1.0.dist-info/WHEEL
abdur_phone_number_validator-0.1.0.dist-info/RECORD
